{
    "version": "0.15.3",
    "description": "A privacy-focussed, local-first, open-source, and ready-to-use alternative for Notion & Miro.",
    "homepage": "https://affine.pro/",
    "license": "MPL-2.0",
    "architecture": {
        "64bit": {
            "url": "https://github.com/toeverything/AFFiNE/releases/download/v0.15.3/affine-0.15.3-stable-windows-x64.exe#/dl.7z",
            "hash": "sha512:9d055e4d246d25d52c3aab9599fec11a2770e86fdb5e36ee6a17c3f4b05907baec53c0a5bd8af693ce6f01cfd0c05b4fa860f2ec4d56ac59fbec0f0e8a45a64d"
        }
    },
    "pre_install": [
        "Expand-7zipArchive \"$dir\\AFFiNE-*-full.nupkg\" -ExtractDir 'lib\\net45' -Removal",
        "Remove-Item \"$dir\\lib\""
    ],
    "shortcuts": [
        [
            "AFFiNE.exe",
            "AFFiNE"
        ]
    ],
    "checkver": {
        "github": "https://github.com/toeverything/AFFiNE"
    },
    "autoupdate": {
        "architecture": {
            "64bit": {
                "url": "https://github.com/toeverything/AFFiNE/releases/download/v$version/affine-$version-stable-windows-x64.exe#/dl.7z",
                "hash": {
                    "url": "$baseurl/latest.yml",
                    "regex": "sha512:\\s+$base64"
                }
            }
        }
    }
}
