{
    "version": "0.8.0",
    "description": "An open-source alternative to Notion. You are in charge of your data and customizations.",
    "homepage": "https://www.appflowy.io/",
    "license": "AGPL-3.0",
    "architecture": {
        "64bit": {
            "url": "https://github.com/AppFlowy-IO/AppFlowy/releases/download/0.8.0/AppFlowy-0.8.0-windows-x86_64.zip",
            "hash": "c17546531633aa91ce99b28251f21e3b000ac5252e72b63a78c0dd3e10d8c0ca"
        }
    },
    "extract_dir": "AppFlowy",
    "shortcuts": [
        [
            "AppFlowy.exe",
            "AppFlowy"
        ]
    ],
    "checkver": {
        "github": "https://github.com/AppFlowy-IO/AppFlowy"
    },
    "autoupdate": {
        "architecture": {
            "64bit": {
                "url": "https://github.com/AppFlowy-IO/AppFlowy/releases/download/$version/AppFlowy-$version-windows-x86_64.zip"
            }
        }
    }
}
