{
    "version": "2.7.5",
    "description": "Opens required browser based on configuration",
    "homepage": "https://www.aloneguid.uk/projects/bt/",
    "license": "Freeware",
    "architecture": {
        "64bit": {
            "url": "https://www.aloneguid.uk/projects/bt/bin/bt-2.7.5.zip",
            "hash": "156c4e353aaab85a5e50e677d54abf8095ca757d55aeac55d9297d8053cde022"
        }
    },
    "bin": "bt.exe",
    "shortcuts": [
        [
            "bt.exe",
            "Browser Tamer"
        ]
    ],
    "checkver": {
        "url": "https://www.aloneguid.uk/projects/bt/bin/latest.txt",
        "regex": "([\\d.]+)"
    },
    "autoupdate": {
        "architecture": {
            "64bit": {
                "url": "https://www.aloneguid.uk/projects/bt/bin/bt-$version.zip"
            }
        }
    }
}
