{
    "version": "1.0.2",
    "description": "CLI library for managing cloud resources such as instances and Kubernetes clusters at Civo.com.",
    "homepage": "https://github.com/civo/cli",
    "license": "Apache-2.0",
    "architecture": {
        "64bit": {
            "url": "https://github.com/civo/cli/releases/download/v1.0.2/civo-1.0.2-windows-amd64.zip",
            "hash": "71c03f22feab8b32134f46fd4f30da7d39ccbe8f2910f0100ed9da1473fe7c2f"
        }
    },
    "bin": "civo.exe",
    "checkver": "github",
    "autoupdate": {
        "architecture": {
            "64bit": {
                "url": "https://github.com/civo/cli/releases/download/v$version/civo-$version-windows-amd64.zip"
            }
        },
        "hash": {
            "url": "$baseurl/civo-$version-checksums.sha256"
        }
    }
}
