{
    "version": "30.7.7521.2",
    "description": "Innovative, powerful and intuitive multiple database management tool",
    "homepage": "https://fishcodelib.com/Database.htm",
    "license": {
        "identifier": "Freeware",
        "url": "https://fishcodelib.com/EULA.htm"
    },
    "url": "https://fishcodelib.com/files/DatabaseNet4.zip",
    "hash": "193bc50f423dd183b14ea2300ec58c1e2d75732ba53701272de3377b2532f93d",
    "shortcuts": [
        [
            "Database4.exe",
            "Database .NET"
        ]
    ],
    "persist": "Database_Files",
    "checkver": {
        "url": "https://fishcodelib.com/version.xml",
        "regex": "database4.*?ver=\"([\\d.]+)\""
    },
    "autoupdate": {
        "url": "https://fishcodelib.com/files/DatabaseNet4.zip"
    }
}
