{
    "version": "95.0a1.20211028223457",
    "description": "Nightly builds of Firefox: the popular open source web browser.",
    "homepage": "https://www.mozilla.org/en-US/firefox/nightly/",
    "license": "MPL-2.0",
    "architecture": {
        "64bit": {
            "url": "https://archive.mozilla.org/pub/firefox/nightly/2021/10/2021-10-28-22-34-57-mozilla-central/firefox-95.0a1.en-US.win64.installer.exe#/dl.7z",
            "hash": "sha512:c6f2d43def95e630f8c8a76d4f5e8e181e9176041bd2948db44b8097f0402d76478f043e5eab96b83ac6360ba1cae45950e5553d5fc5bc317dcc5a24749ffa8e"
        },
        "32bit": {
            "url": "https://archive.mozilla.org/pub/firefox/nightly/2021/10/2021-10-28-22-34-57-mozilla-central/firefox-95.0a1.en-US.win32.installer.exe#/dl.7z",
            "hash": "sha512:7d8fb84aaf3538de06cc5719242c07310aea053d349a7681bda124dfa8866f3437506ff1cbb91c7e48d378216a90133a2d8f28366968b1db2448517119d7f568"
        }
    },
    "extract_dir": "core",
    "bin": [
        [
            "firefox.exe",
            "firefox-nightly"
        ]
    ],
    "shortcuts": [
        [
            "firefox.exe",
            "Firefox Nightly"
        ]
    ],
    "checkver": {
        "url": "https://aus5.mozilla.org/update/6/Firefox/60.0/_/WINNT_x86_64-msvc-x64/en-US/nightly/_/_/_/_/update.xml",
        "regex": "appVersion=\"([\\w.]+)\".*?buildID=\"((?<yyyy>\\d{4})(?<mm>\\d{2})(?<dd>\\d{2})(?<hr>\\d{2})(?<mi>\\d{2})(?<se>\\d{2}))",
        "replace": "${1}.${2}"
    },
    "autoupdate": {
        "architecture": {
            "64bit": {
                "url": "https://archive.mozilla.org/pub/firefox/nightly/$matchYyyy/$matchMm/$matchYyyy-$matchMm-$matchDd-$matchHr-$matchMi-$matchSe-mozilla-central/firefox-$majorVersion.$minorVersion.en-US.win64.installer.exe#/dl.7z",
                "hash": {
                    "url": "$baseurl/firefox-$majorVersion.$minorVersion.en-US.win64.checksums"
                }
            },
            "32bit": {
                "url": "https://archive.mozilla.org/pub/firefox/nightly/$matchYyyy/$matchMm/$matchYyyy-$matchMm-$matchDd-$matchHr-$matchMi-$matchSe-mozilla-central/firefox-$majorVersion.$minorVersion.en-US.win32.installer.exe#/dl.7z",
                "hash": {
                    "url": "$baseurl/firefox-$majorVersion.$minorVersion.en-US.win32.checksums"
                }
            }
        }
    }
}
