{
    "version": "86.0a1.20210117214903",
    "description": "Nightly builds of Firefox: the popular open source web browser.",
    "homepage": "https://www.mozilla.org/en-US/firefox/nightly/",
    "license": "MPL-2.0",
    "architecture": {
        "64bit": {
            "url": "https://archive.mozilla.org/pub/firefox/nightly/2021/01/2021-01-17-21-49-03-mozilla-central/firefox-86.0a1.en-US.win64.installer.exe#/dl.7z",
            "hash": "sha512:940b138bdcaedb5046ed85c41f175b4812b253ac16c1e1af69d1817fce52730157809619583c84169dffbc0f9017537e07943ca08fbd74a7377f46d3527d6c1e"
        },
        "32bit": {
            "url": "https://archive.mozilla.org/pub/firefox/nightly/2021/01/2021-01-17-21-49-03-mozilla-central/firefox-86.0a1.en-US.win32.installer.exe#/dl.7z",
            "hash": "sha512:71ad4ae26a507096435ebb88daa7cedd273ea4066dd7aca7def503744683de634058e4838ca906cbf34bc31cffd44826b0fe41dd59db1df56852e12d84935190"
        }
    },
    "extract_dir": "core",
    "bin": [
        [
            "firefox.exe",
            "firefox-nightly"
        ]
    ],
    "shortcuts": [
        [
            "firefox.exe",
            "Firefox Nightly"
        ]
    ],
    "checkver": {
        "url": "https://aus5.mozilla.org/update/6/Firefox/60.0/_/WINNT_x86_64-msvc-x64/en-US/nightly/_/_/_/_/update.xml",
        "regex": "appVersion=\"([\\w.]+)\".*?buildID=\"((?<yyyy>\\d{4})(?<mm>\\d{2})(?<dd>\\d{2})(?<hr>\\d{2})(?<mi>\\d{2})(?<se>\\d{2}))",
        "replace": "${1}.${2}"
    },
    "autoupdate": {
        "architecture": {
            "64bit": {
                "url": "https://archive.mozilla.org/pub/firefox/nightly/$matchYyyy/$matchMm/$matchYyyy-$matchMm-$matchDd-$matchHr-$matchMi-$matchSe-mozilla-central/firefox-$majorVersion.$minorVersion.en-US.win64.installer.exe#/dl.7z",
                "hash": {
                    "url": "$baseurl/firefox-$majorVersion.$minorVersion.en-US.win64.checksums"
                }
            },
            "32bit": {
                "url": "https://archive.mozilla.org/pub/firefox/nightly/$matchYyyy/$matchMm/$matchYyyy-$matchMm-$matchDd-$matchHr-$matchMi-$matchSe-mozilla-central/firefox-$majorVersion.$minorVersion.en-US.win32.installer.exe#/dl.7z",
                "hash": {
                    "url": "$baseurl/firefox-$majorVersion.$minorVersion.en-US.win32.checksums"
                }
            }
        }
    }
}
