{
    "homepage": "https://flatassembler.net/",
    "description": "Open source assembly language compiler",
    "version": "1.73.17",
    "license": "Unknown",
    "url": "https://flatassembler.net/fasmw17317.zip",
    "hash": "dbe6361fddf5c8b6287b6b23c135e25055d7c12a889d288be597e6491c095ad1",
    "bin": [
        "FASM.EXE",
        "FASMW.EXE"
    ],
    "persist": "FASMW.INI",
    "pre_install": "if(!(Test-Path \"$dir\\FASMW.INI\")) {New-Item (\"$dir\\FASMW.INI\") -Type File | Out-Null}",
    "checkver": {
        "url": "https://flatassembler.net/download.php",
        "regex": "flat assembler ([\\d\\.]+) for Windows"
    },
    "autoupdate": {
        "url": "https://flatassembler.net/fasmw$cleanVersion.zip"
    },
    "shortcuts": [
        [
            "FASMW.EXE",
            "flat assembler"
        ]
    ]
}
