{
    "homepage": "https://freecommander.com",
    "description": "FreeCommander is an easy-to-use alternative to the standard windows file manager",
    "license": {
        "identifier": "Freeware",
        "url": "https://freecommander.com/en/license/"
    },
    "version": "2019",
    "url": "https://freecommander.com/downloads/FreeCommanderXE-32-public_portable.zip",
    "checkver": {
        "url": "https://freecommander.com/en/downloads/",
        "re": "FreeCommander XE ([\\d.]+) Build ([\\d.]+) 32-bit public"
    },
    "hash": "sha1:B3510525B918307667B8D9AA58D65F903D4E5319",
    "bin": "freecommander.exe",
    "shortcuts": [
        [
            "freecommander.exe",
            "Free Commander"
        ]
    ],
    "autoupdate": {
        "url": "https://freecommander.com/downloads/FreeCommanderXE-32-public_portable.zip",
        "hash": {
            "url": "https://freecommander.com/en/downloads/",
            "find": "(?:$basename).*\\(SHA1:\\s+([a-fA-F0-9]{40})"
        }
    }
}
