{
    "version": "82.0.4081.0",
    "description": "Fast, secure, and free web browser, built for the modern web.",
    "homepage": "https://www.google.com/chrome/canary",
    "license": {
        "identifier": "Freeware",
        "url": "https://www.google.com/chrome/privacy/eula_text.html"
    },
    "architecture": {
        "64bit": {
            "url": "https://dl.google.com/release2/chrome/VBG2LKHEp0LabdB2yYPNdA_82.0.4081.0/82.0.4081.0_chrome_installer.exe#/dl.7z",
            "hash": "7e042903ce6333c95f9c4dc7019a03a8fbc94d2f37dc5d802e5a87ef88526c87"
        },
        "32bit": {
            "url": "https://dl.google.com/release2/chrome/OttQm6ZaSezt-rJnRQhMfw_82.0.4081.0/82.0.4081.0_chrome_installer.exe#/dl.7z",
            "hash": "9fbe58fb96f817685f98749ceb916c36e42fa1c1c4182d471c4889e6fb23187c"
        }
    },
    "installer": {
        "script": "Expand-7zipArchive \"$dir\\chrome.7z\" -ExtractDir 'Chrome-bin' -Removal"
    },
    "bin": [
        [
            "chrome.exe",
            "chrome-canary"
        ]
    ],
    "shortcuts": [
        [
            "chrome.exe",
            "Google Chrome (Canary)"
        ]
    ],
    "checkver": {
        "url": "https://chrome-dl.com/api/chrome.min.xml",
        "regex": "(?sm)<canary32><version>(?<version>[\\d.]+)</version>.+release2/chrome/(?<32>[\\w-]+)_.+<canary64>.+release2/chrome/(?<64>[\\w-]+)_.+</canary64>"
    },
    "autoupdate": {
        "architecture": {
            "64bit": {
                "url": "https://dl.google.com/release2/chrome/$match64_$version/$version_chrome_installer.exe#/dl.7z",
                "hash": {
                    "url": "https://chrome-dl.com/api/chrome.min.xml",
                    "xpath": "/chromechecker/canary64[version='$version']/sha256"
                }
            },
            "32bit": {
                "url": "https://dl.google.com/release2/chrome/$match32_$version/$version_chrome_installer.exe#/dl.7z",
                "hash": {
                    "url": "https://chrome-dl.com/api/chrome.min.xml",
                    "xpath": "/chromechecker/canary32[version='$version']/sha256"
                }
            }
        }
    }
}
