{
    "version": "2.09.00",
    "description": "Animation graphic editor easy to use, powerful tool for spriting and pixel art.",
    "homepage": "https://graphicsgale.com/us/",
    "license": "Unknown",
    "url": "https://graphicsgale.com/files/GalePortable20900.zip",
    "hash": "a89d7dc96d560534dd44247e29a5db8a8bcf435983885fabda9c2626f3e0f9bc",
    "shortcuts": [
        [
            "gale.exe",
            "GraphicsGale"
        ],
        [
            "GaleBrowse.exe",
            "GraphicsGale Browser"
        ]
    ],
    "persist": "config",
    "checkver": {
        "url": "https://graphicsgale.com/files/historyUS.txt",
        "regex": "ver\\.([\\d.]+)"
    },
    "autoupdate": {
        "url": "https://graphicsgale.com/files/GalePortable$cleanVersion.zip"
    }
}
