{
    "version": "8.5.1.22",
    "description": "A lightweight, versatile image viewer",
    "homepage": "https://imageglass.org",
    "license": "GPL-3.0-only",
    "notes": "If this app doesn't work maybe you need to clean '$dir\\igconfig.xml'.",
    "architecture": {
        "64bit": {
            "url": "https://github.com/d2phap/ImageGlass/releases/download/8.5.1.22/ImageGlass_8.5.1.22_x64.zip",
            "hash": "sha1:a04de0d9a833c562e2871a1834dabc204d1c76ca",
            "extract_dir": "ImageGlass_8.5.1.22_x64"
        },
        "32bit": {
            "url": "https://github.com/d2phap/ImageGlass/releases/download/8.5.1.22/ImageGlass_8.5.1.22_x86.zip",
            "hash": "sha1:3c9a00bc5c169251021d942f578987d606a43110",
            "extract_dir": "ImageGlass_8.5.1.22_x86"
        }
    },
    "pre_install": [
        "if (!(Test-Path \"$persist_dir\\igconfig.xml\")) {",
        "    Add-Content \"$dir\\igconfig.xml\" '<ImageGlass><Configuration><Info description=\"ImageGlass Configuration file\" version=\"7.5\" /><Info/><Content><Item key=\"AutoUpdate\" value=\"0\" /></Content></Configuration></ImageGlass>' -Encoding Ascii",
        "}"
    ],
    "bin": [
        "ImageGlass.exe",
        "igcmd.exe",
        "igcmdWin10.exe",
        "igtasks.exe"
    ],
    "shortcuts": [
        [
            "ImageGlass.exe",
            "ImageGlass"
        ]
    ],
    "persist": [
        "Themes",
        "igconfig.xml"
    ],
    "checkver": {
        "github": "https://github.com/d2phap/ImageGlass"
    },
    "autoupdate": {
        "architecture": {
            "64bit": {
                "url": "https://github.com/d2phap/ImageGlass/releases/download/$version/ImageGlass_$version_x64.zip",
                "hash": {
                    "url": "https://github.com/d2phap/ImageGlass/releases",
                    "regex": "ImageGlass_[\\d.]+_x64.zip</td>\\n<td><code>$sha1"
                },
                "extract_dir": "ImageGlass_$version_x64"
            },
            "32bit": {
                "url": "https://github.com/d2phap/ImageGlass/releases/download/$version/ImageGlass_$version_x86.zip",
                "hash": {
                    "url": "https://github.com/d2phap/ImageGlass/releases",
                    "regex": "ImageGlass_[\\d.]+_x86.zip</td>\\n<td><code>$sha1"
                },
                "extract_dir": "ImageGlass_$version_x86"
            }
        }
    }
}
