{
    "version": "5.4",
    "description": "Citation and reference management software that uses BibTeX and BibLaTeX as its native formats",
    "homepage": "https://www.jabref.org",
    "license": "MIT",
    "architecture": {
        "64bit": {
            "url": "https://github.com/JabRef/jabref/releases/download/v5.4/JabRef-5.4-portable_windows.zip",
            "hash": "5d2ff2ff5fa676ec1010f49d150c1bb34fc82f1c31e178b7db5249003cd31402"
        }
    },
    "extract_dir": "JabRef",
    "bin": "runtime\\bin\\JabRef.bat",
    "shortcuts": [
        [
            "JabRef.exe",
            "JabRef"
        ]
    ],
    "checkver": {
        "github": "https://github.com/JabRef/jabref"
    },
    "autoupdate": {
        "architecture": {
            "64bit": {
                "url": "https://github.com/JabRef/jabref/releases/download/v$version/JabRef-$version-portable_windows.zip"
            }
        }
    }
}
