{
    "version": "0.24.1552",
    "description": "API Support for your favorite torrent trackers",
    "homepage": "https://github.com/Jackett/Jackett",
    "license": "GPL-2.0-or-later",
    "url": "https://github.com/Jackett/Jackett/releases/download/v0.24.1552/Jackett.Binaries.Windows.zip",
    "hash": "a8b7b5962af1cd1a4f23646228c7d6948e70db5de7483ba2daa358de57ceb1b6",
    "extract_dir": "Jackett",
    "pre_uninstall": [
        "'JacketTray', 'JacketConsole', 'JacketService' | ForEach-Object {",
        "    Stop-Process -Name $_ -ErrorAction SilentlyContinue",
        "}"
    ],
    "shortcuts": [
        [
            "JackettTray.exe",
            "Jackett"
        ]
    ],
    "checkver": "github",
    "autoupdate": {
        "url": "https://github.com/Jackett/Jackett/releases/download/v$version/Jackett.Binaries.Windows.zip"
    }
}
