{
    "version": "0.22.1884",
    "description": "API Support for your favorite torrent trackers",
    "homepage": "https://github.com/Jackett/Jackett",
    "license": "GPL-2.0-or-later",
    "url": "https://github.com/Jackett/Jackett/releases/download/v0.22.1884/Jackett.Binaries.Windows.zip",
    "hash": "37debea89c8e02e6da055579de5a602b8c2a77db3227ff9246f814483343f8bc",
    "extract_dir": "Jackett",
    "pre_uninstall": [
        "'JacketTray', 'JacketConsole', 'JacketService' | ForEach-Object {",
        "    Stop-Process -Name $_ -ErrorAction SilentlyContinue",
        "}"
    ],
    "shortcuts": [
        [
            "JackettTray.exe",
            "Jackett"
        ]
    ],
    "checkver": "github",
    "autoupdate": {
        "url": "https://github.com/Jackett/Jackett/releases/download/v$version/Jackett.Binaries.Windows.zip"
    }
}
