{
    "version": "2.7.14",
    "description": "A note taking and to-do application with synchronization capabilities",
    "homepage": "https://joplinapp.org",
    "license": "MIT",
    "url": "https://github.com/laurent22/joplin/releases/download/v2.7.14/Joplin-Setup-2.7.14.exe#/dl.7z",
    "hash": "sha512:8c371beff9f59d1e29146dd00ac99c6a1230c56ef9ae0cf9ceb4c56308b7538ebdaeb91c79bbcaca3a5b61bd3d9fe4488f41efeed7cbf4000b0024a88634b964",
    "architecture": {
        "64bit": {
            "pre_install": "Expand-7zipArchive \"$dir\\`$PLUGINSDIR\\app-64.7z\" \"$dir\""
        },
        "32bit": {
            "pre_install": "Expand-7zipArchive \"$dir\\`$PLUGINSDIR\\app-32.7z\" \"$dir\""
        }
    },
    "post_install": "Remove-Item \"$dir\\`$*\", \"$dir\\Uninstall*\" -Recurse",
    "bin": "Joplin.exe",
    "shortcuts": [
        [
            "Joplin.exe",
            "Joplin"
        ]
    ],
    "checkver": {
        "github": "https://github.com/laurent22/joplin"
    },
    "autoupdate": {
        "url": "https://github.com/laurent22/joplin/releases/download/v$version/Joplin-Setup-$version.exe#/dl.7z",
        "hash": {
            "url": "$baseurl/latest.yml",
            "regex": "sha512:\\s+$base64"
        }
    }
}
