{
    "version": "2.14.21",
    "description": "A note taking and to-do application with synchronization capabilities",
    "homepage": "https://joplinapp.org",
    "license": "MIT",
    "url": "https://github.com/laurent22/joplin/releases/download/v2.14.21/Joplin-Setup-2.14.21.exe#/dl.7z",
    "hash": "sha512:dd3ced743ba61cf718f50522db7b643c8c0169126045b159fcd80fde012974bd2001f1a4e130cb3243871cb77be034454d8f3fccc4f022849bf6801ecefe8e5c",
    "architecture": {
        "64bit": {
            "pre_install": "Expand-7zipArchive \"$dir\\`$PLUGINSDIR\\app-64.7z\" \"$dir\""
        },
        "32bit": {
            "pre_install": "Expand-7zipArchive \"$dir\\`$PLUGINSDIR\\app-32.7z\" \"$dir\""
        }
    },
    "post_install": "Remove-Item \"$dir\\`$*\", \"$dir\\Uninstall*\" -Recurse",
    "bin": "Joplin.exe",
    "shortcuts": [
        [
            "Joplin.exe",
            "Joplin"
        ]
    ],
    "checkver": {
        "github": "https://github.com/laurent22/joplin"
    },
    "autoupdate": {
        "url": "https://github.com/laurent22/joplin/releases/download/v$version/Joplin-Setup-$version.exe#/dl.7z",
        "hash": {
            "url": "$baseurl/latest.yml",
            "regex": "sha512:\\s+$base64"
        }
    }
}
