{
    "version": "5.5.1",
    "description": "Comic and manga converter for ebook readers.",
    "homepage": "https://github.com/ciromattia/kcc",
    "license": "ISC",
    "architecture": {
        "64bit": {
            "url": "https://kcc.iosphe.re/Windows/KindleComicConverter_win_5.5.1.exe",
            "hash": "3a4468c630b368eff0e3b6c67ebe85484ff145163f59666e40735369da58c63b",
            "shortcuts": [
                [
                    "KCC.exe",
                    "Kindle Comic Converter"
                ]
            ]
        }
    },
    "innosetup": true,
    "depends": "extras/kindlegen",
    "checkver": "github",
    "autoupdate": {
        "architecture": {
            "64bit": {
                "url": "https://kcc.iosphe.re/Windows/KindleComicConverter_win_$version.exe"
            }
        }
    }
}
