{
    "version": "2.7.1",
    "description": "Community fork of KeePass",
    "homepage": "https://keepassxc.org",
    "license": "GPL-2.0-only",
    "architecture": {
        "64bit": {
            "url": "https://github.com/keepassxreboot/keepassxc/releases/download/2.7.1/KeePassXC-2.7.1-Win64.zip",
            "hash": "5b4e53141886f97cec1b451b33dc714d6c9af2ac9b69af22304fa7cedf76b774",
            "extract_dir": "KeePassXC-2.7.1-Win64"
        }
    },
    "post_install": "if (Test-Path \"$persist_dir\\keepassxc.ini\") { Move-Item \"$persist_dir\\keepassxc.ini\" \"$dir\\config\" -Force }",
    "bin": [
        "KeePassXC.exe",
        "keepassxc-cli.exe",
        "keepassxc-proxy.exe"
    ],
    "shortcuts": [
        [
            "KeePassXC.exe",
            "KeePassXC"
        ]
    ],
    "persist": "config",
    "checkver": {
        "github": "https://github.com/keepassxreboot/keepassxc"
    },
    "autoupdate": {
        "architecture": {
            "64bit": {
                "url": "https://github.com/keepassxreboot/keepassxc/releases/download/$version/KeePassXC-$version-Win64.zip",
                "extract_dir": "KeePassXC-$version-Win64"
            }
        },
        "hash": {
            "url": "$url.DIGEST"
        }
    }
}
