{
    "version": "7.0.1",
    "description": "Universal development environment for PHP, Node.js, Python, Java, Go, Ruby",
    "homepage": "https://laragon.org/",
    "license": "MIT",
    "innosetup": true,
    "url": "https://github.com/leokhoa/laragon/releases/download/7.0.1/laragon-wamp.exe",
    "hash": "482a3c3a1c222b86c7cc91a78d7e16cfb264b75a1efca6e5a4a6b0f58d3d0380",
    "shortcuts": [
        [
            "laragon.exe",
            "Laragon"
        ]
    ],
    "persist": [
        "etc",
        "tmp",
        "usr",
        "www"
    ],
    "checkver": {
        "github": "https://github.com/leokhoa/laragon"
    },
    "autoupdate": {
        "url": "https://github.com/leokhoa/laragon/releases/download/$version/laragon-wamp.exe"
    }
}
