{
    "version": "1.23.16.1",
    "description": "Markdown editing and weblog publishing tool.",
    "homepage": "https://markdownmonster.west-wind.com",
    "license": {
        "identifier": "Proprietary",
        "url": "https://markdownmonster.west-wind.com/purchase.aspx#License"
    },
    "url": "https://west-wind.com/files/MarkdownMonsterPortable.zip",
    "hash": "3012775bf803fc7bdc6fbe0b12ecc283531cac3674ef73b774cf45197efe25e5",
    "bin": [
        "mm.exe",
        "MarkdownMonster.exe"
    ],
    "shortcuts": [
        [
            "MarkdownMonster.exe",
            "Markdown Monster"
        ]
    ],
    "persist": "PortableSettings",
    "checkver": {
        "url": "https://markdownmonster.west-wind.com/download.aspx",
        "regex": "<[vV]ersion>([\\d.]+)</[vV]ersion>"
    },
    "autoupdate": {
        "url": "https://west-wind.com/files/MarkdownMonsterPortable.zip"
    }
}
