{
    "version": "7.1.1",
    "description": "Visualizer for deep learning and machine learning models",
    "homepage": "https://netron.app/",
    "license": "MIT",
    "architecture": {
        "64bit": {
            "url": "https://github.com/lutzroeder/netron/releases/download/v7.1.1/Netron-Setup-7.1.1.exe#/dl.7z",
            "hash": "sha512:f076f7346f1839c07194c8f20d8fc46115a3e085941c730c2bdf27f63965ce0feb1998ed6d598bcb74579005d10920752e7fe6ebc82a31bb512a71c485e015a4",
            "pre_install": [
                "Expand-7zipArchive \"$dir\\`$PLUGINSDIR\\app-64.7z\" \"$dir\"",
                "Remove-Item \"$dir\\`$*\" -Force -Recurse"
            ]
        }
    },
    "bin": "Netron.exe",
    "shortcuts": [
        [
            "Netron.exe",
            "Netron"
        ]
    ],
    "checkver": {
        "github": "https://github.com/lutzroeder/netron"
    },
    "autoupdate": {
        "architecture": {
            "64bit": {
                "url": "https://github.com/lutzroeder/netron/releases/download/v$version/Netron-Setup-$version.exe#/dl.7z",
                "hash": {
                    "url": "$baseurl/latest.yml",
                    "regex": "sha512:\\s+$base64"
                }
            }
        }
    }
}
