{
    "version": "0.1.327",
    "description": "Open source singing synthesis platform",
    "homepage": "https://github.com/stakira/OpenUtau/",
    "license": "MIT",
    "architecture": {
        "64bit": {
            "url": "https://github.com/stakira/OpenUtau/releases/download/build%2F0.1.327/OpenUtau-win-x64.zip",
            "hash": "631e330af77f57f87050ae0d9cbd85f235b085f3d61bc130abd383a10ec2e9fc"
        },
        "32bit": {
            "url": "https://github.com/stakira/OpenUtau/releases/download/build%2F0.1.327/OpenUtau-win-x86.zip",
            "hash": "a001f556e99ae65d86cb70dfceb60a7a196b270eb1cb5b67b3ce276b85770ae3"
        }
    },
    "bin": "OpenUtau.exe",
    "shortcuts": [
        [
            "OpenUtau.exe",
            "OpenUtau"
        ]
    ],
    "persist": [
        "Backups",
        "Cache",
        "Dictionaries",
        "Plugins",
        "Resamplers",
        "Singers",
        "Templates",
        "Wavtools"
    ],
    "checkver": {
        "url": "https://github.com/stakira/OpenUtau/releases/latest",
        "regex": "build\\/(?:v|V)?([\\d.]+)"
    },
    "autoupdate": {
        "architecture": {
            "64bit": {
                "url": "https://github.com/stakira/OpenUtau/releases/download/build%2F$version/OpenUtau-win-x64.zip"
            },
            "32bit": {
                "url": "https://github.com/stakira/OpenUtau/releases/download/build%2F$version/OpenUtau-win-x86.zip"
            }
        }
    }
}
