{
    "version": "3.4.1",
    "description": "The practical and pragmatic code editor.",
    "homepage": "https://pragtical.github.io",
    "license": "MIT",
    "architecture": {
        "64bit": {
            "url": "https://github.com/pragtical/pragtical/releases/download/v3.4.1/pragtical-v3.4.1-windows-x86_64.zip",
            "hash": "AF3A4182321679FEE1DAA4BD75E234E8C5ACCC239381F52AD5FC76D711ED66E5"
        },
        "32bit": {
            "url": "https://github.com/pragtical/pragtical/releases/download/v3.4.1/pragtical-v3.4.1-windows-i686.zip",
            "hash": "739E72361F3B7819176C5C830B20D3528A1F429950F785E4E5637D67E3B48C72"
        }
    },
    "extract_dir": "pragtical",
    "bin": "pragtical.exe",
    "shortcuts": [
        [
            "pragtical.exe",
            "Pragtical"
        ]
    ],
    "checkver": {
        "github": "https://github.com/pragtical/pragtical"
    },
    "autoupdate": {
        "architecture": {
            "64bit": {
                "url": "https://github.com/pragtical/pragtical/releases/download/v$version/pragtical-v$version-windows-x86_64.zip",
            },
            "32bit": {
                "url": "https://github.com/pragtical/pragtical/releases/download/v$version/pragtical-v$version-windows-i686.zip",
            }
        }
    }
}
