{
    "version": "24.1.0",
    "description": "Plain-text notepad and todo-list manager with markdown support and Nextcloud / ownCloud integration",
    "homepage": "https://www.qownnotes.org/",
    "license": "GPL-2.0-only",
    "architecture": {
        "64bit": {
            "url": "https://github.com/pbek/QOwnNotes/releases/download/v24.1.0/QOwnNotes.zip",
            "hash": "fb95c0816e2efc32d631b0f2b9fb555359b7c73cdaf810d70dd84c8ecbc8c594"
        }
    },
    "shortcuts": [
        [
            "QOwnNotes.exe",
            "QOwnNotes",
            "--portable"
        ]
    ],
    "persist": "Data",
    "checkver": {
        "github": "https://github.com/pbek/QOwnNotes"
    },
    "autoupdate": {
        "architecture": {
            "64bit": {
                "url": "https://github.com/pbek/QOwnNotes/releases/download/v$version/QOwnNotes.zip"
            }
        }
    }
}
