{
    "version": "5.6.1",
    "description": "SCIntilla based Text Editor",
    "homepage": "https://www.scintilla.org/SciTE.html",
    "license": "HPND",
    "architecture": {
        "64bit": {
            "url": "https://www.scintilla.org/Sc561.exe#/Sc1.exe",
            "hash": "1c82844e7aeb70774e565600be71034a50ed4aa6aab896515ec4485c8e49a605"
        }
    },
    "bin": "Sc1.exe",
    "shortcuts": [
        [
            "Sc1.exe",
            "Sc1"
        ]
    ],
    "checkver": "Release version ([\\d.]+)",
    "autoupdate": {
        "url": "https://www.scintilla.org/Sc$cleanVersion.exe#/Sc1.exe"
    }
}
