{
    "version": "2.11.0",
    "description": "A command line tool that facilitates continuous development for Kubernetes applications.",
    "homepage": "https://skaffold.dev",
    "license": "Apache-2.0",
    "architecture": {
        "64bit": {
            "url": "https://github.com/GoogleCloudPlatform/skaffold/releases/download/v2.11.0/skaffold-windows-amd64.exe#/skaffold.exe",
            "hash": "8086cc1e5d84e3b54558c341000db17f3b4211a5674f01999bbfb4e708611224"
        }
    },
    "bin": "skaffold.exe",
    "checkver": {
        "github": "https://github.com/GoogleCloudPlatform/skaffold"
    },
    "autoupdate": {
        "architecture": {
            "64bit": {
                "url": "https://github.com/GoogleCloudPlatform/skaffold/releases/download/v$version/skaffold-windows-amd64.exe#/skaffold.exe"
            }
        },
        "hash": {
            "url": "$url.sha256"
        }
    }
}
