{
    "version": "1.7.6",
    "description": "Tray application for Syncthing",
    "homepage": "https://github.com/Martchus/syncthingtray",
    "license": {
        "identifier": "GPL-2.0-only,...",
        "url": "https://github.com/Martchus/syncthingtray/blob/master/LICENSES-windows-distribution.md"
    },
    "architecture": {
        "64bit": {
            "url": "https://github.com/Martchus/syncthingtray/releases/download/v1.7.6/syncthingtray-1.7.6-x86_64-w64-mingw32.exe.zip",
            "hash": "96bcbfe03fedac69b66ec3871f24e223f82139b18a63a7f42d818129b6187365"
        },
        "32bit": {
            "url": "https://github.com/Martchus/syncthingtray/releases/download/v1.7.6/syncthingtray-qt5-1.7.6-i686-w64-mingw32.exe.zip",
            "hash": "0edb033c24fe33a80f59566bb339d1d4c8ab5bb227d515c54d27706b99beb116"
        },
        "arm64": {
            "url": "https://github.com/Martchus/syncthingtray/releases/download/v1.7.6/syncthingtray-1.7.6-aarch64-w64-mingw32.exe.zip",
            "hash": "96e90ebb57528d9e1bb4b354ea912762d7bf6b1ef6d1b4270d7ff0829ab0b31d"
        }
    },
    "pre_install": [
        "Move-Item \"$dir\\syncthingtray-*-mingw32.exe\" \"$dir\\syncthingtray.exe\"",
        "Move-Item \"$dir\\syncthingtray-*-mingw32-cli.exe\" \"$dir\\syncthingtray-cli.exe\""
    ],
    "##": "syncthingtray.ini will recreate by syncthingtray.exe",
    "post_install": [
        "$config = \"syncthingtray.ini\"",
        "ensure $persist_dir",
        "if (!(Test-Path \"$persist_dir\\$config\")) { New-Item \"$persist_dir\\$config\" -ItemType File | Out-Null }",
        "move-item \"$persist_dir\\$config\" \"$dir\""
    ],
    "pre_uninstall": [
        "ensure $persist_dir",
        "move-item \"$dir\\syncthingtray.ini\" \"$persist_dir\""
    ],
    "bin": "syncthingtray-cli.exe",
    "shortcuts": [
        [
            "syncthingtray.exe",
            "Syncthing Tray"
        ]
    ],
    "checkver": "github",
    "autoupdate": {
        "architecture": {
            "64bit": {
                "url": "https://github.com/Martchus/syncthingtray/releases/download/v$version/syncthingtray-$version-x86_64-w64-mingw32.exe.zip"
            },
            "32bit": {
                "url": "https://github.com/Martchus/syncthingtray/releases/download/v$version/syncthingtray-qt5-$version-i686-w64-mingw32.exe.zip"
            },
            "arm64": {
                "url": "https://github.com/Martchus/syncthingtray/releases/download/v$version/syncthingtray-$version-aarch64-w64-mingw32.exe.zip"
            }
        }
    }
}
