{
    "version": "78.2.0",
    "description": "A free email application that’s easy to set up and customize.",
    "homepage": "https://www.thunderbird.net",
    "license": "MPL-2.0",
    "architecture": {
        "64bit": {
            "url": "https://archive.mozilla.org/pub/thunderbird/releases/78.2.0/win64/en-US/Thunderbird%20Setup%2078.2.0.exe#/dl.7z",
            "hash": "sha512:89ce90db42133beb6a788dd596a6daa8b231bfe5cea0a3720af0b42b02129db4bfd973cf8952c71ee21d51e7ecabe2ca8e6606505e978036122ec1bc90346032"
        },
        "32bit": {
            "url": "https://archive.mozilla.org/pub/thunderbird/releases/78.2.0/win32/en-US/Thunderbird%20Setup%2078.2.0.exe#/dl.7z",
            "hash": "sha512:e98c40bcf0e576d31d5aeac1b1ab59a82a7b132381c1212eb4db426df62c31543cec25d3066eebf9f422387cf02556f97815b0aff09e745e0e2c0fa1c5e81e8c"
        }
    },
    "extract_dir": "core",
    "bin": [
        [
            "thunderbird.exe",
            "thunderbird",
            "-profile \"$dir\\profile\""
        ]
    ],
    "shortcuts": [
        [
            "thunderbird.exe",
            "Mozilla Thunderbird",
            "-profile \"$dir\\profile\""
        ]
    ],
    "persist": "profile",
    "checkver": {
        "url": "https://www.thunderbird.net/thunderbird/all/",
        "regex": "thunderbird/([\\d.]+)/"
    },
    "autoupdate": {
        "architecture": {
            "64bit": {
                "url": "https://archive.mozilla.org/pub/thunderbird/releases/$version/win64/en-US/Thunderbird%20Setup%20$version.exe#/dl.7z",
                "hash": {
                    "url": "https://archive.mozilla.org/pub/thunderbird/releases/$version/SHA512SUMS",
                    "regex": "$sha512\\s+win64/en-US/$basename"
                }
            },
            "32bit": {
                "url": "https://archive.mozilla.org/pub/thunderbird/releases/$version/win32/en-US/Thunderbird%20Setup%20$version.exe#/dl.7z",
                "hash": {
                    "url": "https://archive.mozilla.org/pub/thunderbird/releases/$version/SHA512SUMS",
                    "regex": "$sha512\\s+win32/en-US/$basename"
                }
            }
        }
    }
}
