{
    "version": "2.8.85",
    "description": "VNC-Compatible Remote Control / Remote Desktop",
    "homepage": "https://tightvnc.com",
    "license": "GPL-2.0-or-later",
    "architecture": {
        "64bit": {
            "url": "https://www.tightvnc.com/download/2.8.85/tightvnc-2.8.85-gpl-setup-64bit.msi",
            "hash": "d8fbed7b27ebab86df6f780f6e86f723668f3715cee521ccaa4568812aef5f3e"
        },
        "32bit": {
            "url": "https://www.tightvnc.com/download/2.8.85/tightvnc-2.8.85-gpl-setup-32bit.msi",
            "hash": "a4929bb1dcfc7aa245a44e8b4b7240cccc94bcad7240282409c144efe3912ae9"
        }
    },
    "extract_dir": "PFiles\\TightVNC",
    "bin": [
        "tvnviewer.exe",
        "tvnserver.exe"
    ],
    "shortcuts": [
        [
            "tvnviewer.exe",
            "TightVNC Viewer"
        ],
        [
            "tvnserver.exe",
            "TightVNC Server"
        ]
    ],
    "checkver": {
        "url": "https://www.tightvnc.com/download.php",
        "regex": "\\(Version ([\\d.]+)\\)"
    },
    "autoupdate": {
        "architecture": {
            "64bit": {
                "url": "https://www.tightvnc.com/download/$version/tightvnc-$version-gpl-setup-64bit.msi"
            },
            "32bit": {
                "url": "https://www.tightvnc.com/download/$version/tightvnc-$version-gpl-setup-32bit.msi"
            }
        }
    }
}
