{
    "version": "1.8.6",
    "description": "A minimal Markdown editor and reader",
    "homepage": "https://typora.io",
    "license": {
        "identifier": "Proprietary",
        "url": "https://support.typora.io/License-Agreement/"
    },
    "notes": "For old beta version, install: versions/typora0.11.18",
    "architecture": {
        "64bit": {
            "url": "https://download.typora.io/windows/typora-setup-x64-1.8.6.exe",
            "hash": "66b439b76771eb02d11f186a1994842959f1db2921ed465efd9b83a301859912"
        },
        "32bit": {
            "url": "https://download.typora.io/windows/typora-setup-ia32-1.8.6.exe",
            "hash": "f55fca6f71e51c23ea602842999fdae9e9d90631e3218af9d976784319d721dd"
        }
    },
    "innosetup": true,
    "bin": "Typora.exe",
    "shortcuts": [
        [
            "Typora.exe",
            "Typora"
        ]
    ],
    "checkver": {
        "url": "https://typora.io/releases/stable",
        "regex": "<h2>([\\d.]+)"
    },
    "autoupdate": {
        "architecture": {
            "64bit": {
                "url": "https://download.typora.io/windows/typora-setup-x64-$version.exe"
            },
            "32bit": {
                "url": "https://download.typora.io/windows/typora-setup-ia32-$version.exe"
            }
        }
    }
}
