{
    "version": "2.1.14",
    "description": "Full featured gcode platform used for interfacing with advanced CNC controllers.",
    "homepage": "https://winder.github.io/ugs_website/",
    "license": "GPL-3.0-only",
    "extract_dir": "ugsplatform-win",
    "architecture": {
        "64bit": {
            "url": "https://github.com/winder/Universal-G-Code-Sender/releases/download/v2.1.14/win64-ugs-platform-app-2.1.14.zip",
            "hash": "b2b5fbe7e4e0f7cce9038185a2a0c62cfbdad12a35cc91be747dab3d358c2fc0",
            "bin": [
                [
                    "bin\\ugsplatform64.exe",
                    "ugsplatform"
                ]
            ],
            "shortcuts": [
                [
                    "bin\\ugsplatform64.exe",
                    "UGS Platform"
                ]
            ]
        },
        "32bit": {
            "url": "https://github.com/winder/Universal-G-Code-Sender/releases/download/v2.1.14/win-ugs-platform-app-2.1.14.zip",
            "hash": "a8094d7fba450a60d39ceca3976626d277e36d9776b088bcd322e46ec7eba4c9",
            "bin": "bin\\ugsplatform.exe",
            "shortcuts": [
                [
                    "bin\\ugsplatform.exe",
                    "UGS Platform"
                ]
            ]
        }
    },
    "checkver": {
        "github": "https://github.com/winder/Universal-G-Code-Sender"
    },
    "autoupdate": {
        "architecture": {
            "64bit": {
                "url": "https://github.com/winder/Universal-G-Code-Sender/releases/download/v$version/win64-ugs-platform-app-$version.zip"
            },
            "32bit": {
                "url": "https://github.com/winder/Universal-G-Code-Sender/releases/download/v$version/win-ugs-platform-app-$version.zip"
            }
        }
    }
}
