{
    "homepage": "https://vivaldi.com/",
    "description": "An innovatively designed web browser, based on Blink, for users in Vivaldi.net community that replaced departed My Opera",
    "version": "2.3.1440.61",
    "license": {
        "identifier": "freeware,BSD",
        "url": "https://vivaldi.com/privacy/vivaldi-end-user-license-agreement/"
    },
    "architecture": {
        "64bit": {
            "url": "https://downloads.vivaldi.com/stable/Vivaldi.2.3.1440.61.x64.exe#/dl.7z",
            "hash": "14a376cbfa674542a80b91d624e6615dae3dc4040134762d8cece6eb34b9fab0"
        },
        "32bit": {
            "url": "https://downloads.vivaldi.com/stable/Vivaldi.2.3.1440.61.exe#/dl.7z",
            "hash": "f86f8b5be4d16b4dc1695fa63f9ab1ab36c8cbcf71078ee6c91c7e58493cba7d"
        }
    },
    "installer": {
        "script": [
            "extract_7zip \"$dir\\vivaldi.7z\" \"$dir\"",
            "Move-Item \"$dir\\Vivaldi-bin\" \"$dir\\Application\"",
            "Remove-Item \"$dir\\vivaldi.7z\"",
            "Remove-Item \"$dir\\Application\\update_notifier.exe\"",
            "Write-Output \"// Vivaldi Standalone\" | Set-Content \"$dir\\Application\\stp.viv\""
        ]
    },
    "bin": "Application\\vivaldi.exe",
    "shortcuts": [
        [
            "Application\\vivaldi.exe",
            "Vivaldi"
        ]
    ],
    "persist": "User Data",
    "checkver": {
        "url": "https://vivaldi.com/download/",
        "re": "Vivaldi\\.([\\d.]+)\\.exe"
    },
    "autoupdate": {
        "architecture": {
            "64bit": {
                "url": "https://downloads.vivaldi.com/stable/Vivaldi.$version.x64.exe#/dl.7z"
            },
            "32bit": {
                "url": "https://downloads.vivaldi.com/stable/Vivaldi.$version.exe#/dl.7z"
            }
        }
    }
}
