{
    "homepage": "https://www.whatsapp.com",
    "version": "0.2.9998",
    "license": "Commercial",
    "architecture": {
        "32bit": {
            "url": "https://web.whatsapp.com/desktop/windows/release/ia32/WhatsApp-0.2.9998-full.nupkg#/dl.7z",
            "hash": "8e47374133bb88ca6f7eaa9393840e09799adc18fbdf3457ee9a018a2800a5ba"
        },
        "64bit": {
            "url": "https://web.whatsapp.com/desktop/windows/release/x64/WhatsApp-0.2.9998-full.nupkg#/dl.7z",
            "hash": "83fe77615d9a78abe21e69c169c352a6b94162fba2bd3c2957b84f28d33e194d"
        }
    },
    "extract_dir": "lib\\net45",
    "bin": "whatsapp.exe",
    "shortcuts": [
        [
            "whatsapp.exe",
            "WhatsApp"
        ]
    ],
    "checkver": {
        "url": "https://web.whatsapp.com/desktop/windows/release/x64/RELEASES",
        "re": "WhatsApp-([\\d.]+)-full.nupkg",
        "reverse": true
    },
    "autoupdate": {
        "architecture": {
            "32bit": {
                "url": "https://web.whatsapp.com/desktop/windows/release/ia32/WhatsApp-$version-full.nupkg#/dl.7z"
            },
            "64bit": {
                "url": "https://web.whatsapp.com/desktop/windows/release/x64/WhatsApp-$version-full.nupkg#/dl.7z"
            }
        },
        "hash": {
            "url": "$baseurl/RELEASES"
        }
    }
}
